daplis_rtp/__init__.py
daplis_rtp/main.py
daplis_rtp/functions/__init__.py
daplis_rtp/functions/calibrate.py
daplis_rtp/functions/sen_pop.py
daplis_rtp/functions/unpack.py
daplis_rtp/functions/old/calc_diff_old.py
daplis_rtp/functions/old/sen_pop_old.py
daplis_rtp/functions/old/unpack_old.py
daplis_rtp/gui/MZI_tab.py
daplis_rtp/gui/__init__.py
daplis_rtp/gui/live_timestamps_tab.py
daplis_rtp/gui/plot_figure.py
daplis_rtp/gui/plot_figure_MZI.py
daplis_rtp/gui/single_pix_hist_tab.py
daplis_rtp/gui/single_pixel_histogram.py
daplis_rtp/gui/_old/delta_t_plot.py
daplis_rtp/gui/_old/delta_t_tab.py
daplis_rtp/gui/_old/tab_livetimestamps.py
daplis_rtp/gui/_old/tab_widget.py
daplis_rtp/gui/ui/LiveTimestamps_tab_c.py
daplis_rtp/gui/ui/MZI_tab.py
daplis_rtp/gui/ui/SinglePixelHistogram_tab_c.py
daplis_rtp/gui/ui/mainwindow.py
daplis_rtp/gui/ui/_old/LiveTimestamps_tab_c - Copy.py
daplis_rtp/gui/ui/_old/LiveTimestamps_tab_ui.py
daplis_rtp/gui/ui/_old/SinglePixelHistogram_ui.py
daplis_rtp/params/calibration_data/Calibration_data_A5.csv
daplis_rtp/params/calibration_data/Calibration_data_NL11.csv
daplis_rtp/params/masks/mask_A5.txt
daplis_rtp/params/masks/mask_B7d_#28.txt
daplis_rtp/params/masks/mask_D2b_#4.txt
daplis_rtp/params/masks/mask_NL11.txt
daplis_rtp/params/masks/mask_NL11_#21.txt
daplis_rtp/params/masks/mask_NL11_#21_pix_add_not_fixed.txt
daplis_rtp/params/masks/mask_NL11_#33.txt
daplis_rtp/params/masks/mask_NL11_all.txt
daplis_rtp-1.2.0.dist-info/licenses/LICENSE
daplis_rtp-1.2.0.dist-info/METADATA
daplis_rtp-1.2.0.dist-info/WHEEL
daplis_rtp-1.2.0.dist-info/entry_points.txt
daplis_rtp-1.2.0.dist-info/top_level.txt
daplis_rtp-1.2.0.dist-info/RECORD
