Metadata-Version: 2.4
Name: daplis-rtp
Version: 1.2.0
Summary: Data Analysis Package for LInoSpad - Real-Time Plotting
Author-email: Sergei Kulkov <sergei.kulkov23@gmail.com>
License: MIT
Project-URL: Homepage, https://github.com/rngKomorebi/daplis-rtp
Keywords: timestamp,analysis,LinoSPAD2
Classifier: Programming Language :: Python :: 3.8
Classifier: Programming Language :: Python :: 3.9
Classifier: Programming Language :: Python :: 3.10
Classifier: Programming Language :: Python :: 3.11
Classifier: Programming Language :: Python :: 3.12
Classifier: Programming Language :: Python :: 3.13
Requires-Python: >=3.8
License-File: LICENSE
Requires-Dist: matplotlib>=3.6.2
Requires-Dist: numpy>=1.23.5
Requires-Dist: PyQt5>=5.15.7
Requires-Dist: setuptools>=70.0
Requires-Dist: qdarkstyle>=3.2.0
Dynamic: license-file
